rlapi/VERSION
rlapi/__init__.py
rlapi/_utils.py
rlapi/client.py
rlapi/enums.py
rlapi/errors.py
rlapi/leaderboard.py
rlapi/player.py
rlapi/player_titles.py
rlapi/population.py
rlapi/py.typed
rlapi/tier_estimates.py
rlapi/typedefs.py
rlapi/ext/tier_breakdown/__init__.py
rlapi/ext/tier_breakdown/py.typed
rlapi/ext/tier_breakdown/rlstatsnet.py
rlapi-0.8.0b1.dist-info/LICENSE
rlapi-0.8.0b1.dist-info/METADATA
rlapi-0.8.0b1.dist-info/WHEEL
rlapi-0.8.0b1.dist-info/top_level.txt
rlapi-0.8.0b1.dist-info/RECORD
