Metadata-Version: 2.1
Name: rlapi
Version: 0.8.0b1
Summary: Async ready API wrapper for Rocket League API
Home-page: https://github.com/Jackenmen/rlapi
Author: Jakub Kuczys (Jackenmen)
License: Apache License 2.0
Project-URL: Documentation, https://rlapi.readthedocs.io
Project-URL: Donate on Patreon, https://www.patreon.com/Jackenmen
Project-URL: Issue Tracker, https://github.com/Jackenmen/rlapi/issues
Project-URL: Source Code, https://github.com/Jackenmen/rlapi
Platform: UNKNOWN
Classifier: Development Status :: 4 - Beta
Classifier: Framework :: AsyncIO
Classifier: Intended Audience :: Developers
Classifier: License :: OSI Approved :: Apache Software License
Classifier: Natural Language :: English
Classifier: Operating System :: OS Independent
Classifier: Programming Language :: Python :: 3.8
Classifier: Programming Language :: Python :: 3.9
Classifier: Programming Language :: Python :: 3.10
Classifier: Programming Language :: Python :: 3.11
Classifier: Programming Language :: Python :: 3.12
Classifier: Programming Language :: Python :: 3.13
Classifier: Topic :: Internet
Classifier: Topic :: Software Development :: Libraries
Classifier: Topic :: Software Development :: Libraries :: Python Modules
Classifier: Topic :: Utilities
Classifier: Typing :: Typed
Requires-Python: >=3.8
Requires-Dist: aiohttp<4.0,>=3.5.4
Requires-Dist: lxml<6.0,>=4.4.2
Provides-Extra: docs
Requires-Dist: sphinx<5.0,>=4.5.0; extra == "docs"
Requires-Dist: sphinxcontrib-trio<1.2,>=1.1.2; extra == "docs"
Requires-Dist: sphinx-rtd-theme; extra == "docs"
Provides-Extra: lint
Requires-Dist: flake8<5.0,>=4.0.1; extra == "lint"
Provides-Extra: style
Requires-Dist: black<23,>22.1.0; extra == "style"
Requires-Dist: isort<6,==5.10.1; extra == "style"
Provides-Extra: tests
Requires-Dist: mypy==1.12.1; extra == "tests"
